pyrot/__init__.py
pyrot/_tools.py
pyrot/cavity1d.py
pyrot/cavityatoms1d.py
pyrot-0.0.1.dist-info/LICENSE.txt
pyrot-0.0.1.dist-info/METADATA
pyrot-0.0.1.dist-info/WHEEL
pyrot-0.0.1.dist-info/top_level.txt
pyrot-0.0.1.dist-info/RECORD
